quickmlops/__init__.py
quickmlops/__main__.py
quickmlops/main.py
quickmlops/quickmlops/__init__.py
quickmlops/quickmlops/build.py
quickmlops/quickmlops/config_help.py
quickmlops/quickmlops/constants.py
quickmlops/quickmlops/delete.py
quickmlops/quickmlops/utils.py
quickmlops/quickmlops/templates/__init__.py
quickmlops/quickmlops/templates/__main__.py
quickmlops/quickmlops/templates/docker/__init__.py
quickmlops/quickmlops/templates/flask/__init__.py
quickmlops/quickmlops/templates/flask/serve.py
quickmlops/quickmlops/templates/pytorch/__init__.py
quickmlops/quickmlops/templates/pytorch/models.py
quickmlops/quickmlops/templates/pytorch/train.py
quickmlops/quickmlops/templates/pytorch/utils.py
quickmlops/quickmlops/templates/scikit_learn/__init__.py
quickmlops/quickmlops/templates/scikit_learn/train.py
quickmlops/quickmlops/templates/scikit_learn/utils.py
quickmlops-0.0.1.dist-info/METADATA
quickmlops-0.0.1.dist-info/WHEEL
quickmlops-0.0.1.dist-info/top_level.txt
quickmlops-0.0.1.dist-info/RECORD
